opentelemetry_ext_newrelic/__init__.py
opentelemetry_ext_newrelic/span.py
opentelemetry_ext_newrelic/version.py
opentelemetry_ext_newrelic-0.1.1.dist-info/LICENSE
opentelemetry_ext_newrelic-0.1.1.dist-info/METADATA
opentelemetry_ext_newrelic-0.1.1.dist-info/WHEEL
opentelemetry_ext_newrelic-0.1.1.dist-info/top_level.txt
opentelemetry_ext_newrelic-0.1.1.dist-info/RECORD
