Metadata-Version: 2.1
Name: opentelemetry-ext-newrelic
Version: 0.1.1
Summary: New Relic OpenTelemetry Exporter
Home-page: https://github.com/newrelic/opentelemetry-exporter-python
Author: New Relic
Author-email: opensource@newrelic.com
License: Apache-2.0
Platform: any
Classifier: Development Status :: 3 - Alpha
Classifier: Topic :: System :: Monitoring
Classifier: Programming Language :: Python :: Implementation :: PyPy
Classifier: Programming Language :: Python :: Implementation :: CPython
Classifier: Programming Language :: Python :: 3
Classifier: Programming Language :: Python :: 3.5
Classifier: Programming Language :: Python :: 3.6
Classifier: Programming Language :: Python :: 3.7
Classifier: Programming Language :: Python :: 3.8
Classifier: Operating System :: OS Independent
Classifier: License :: OSI Approved :: Apache Software License
Requires-Python: >=3.5
Requires-Dist: opentelemetry-sdk (>=0.15b0)
Requires-Dist: newrelic-telemetry-sdk (<0.5,>=0.4.0)
